structura_py/__init__.py
structura_py/cli.py
structura_py/commands/__init__.py
structura_py/commands/init.py
structura_py/models/__init__.py
structura_py/models/architecture_model.py
structura_py/models/dependency_model.py
structura_py/models/project_model.py
structura_py/templates/default_dependencies.yaml
structura_py/templates/fastapi_server.yaml
structura_py/templates/flask_server.yaml
structura_py/templates/hexagonal.yaml
structura_py/templates/initial_structure.yaml
structura_py/templates/mvc-api.yaml
structura_py/templates/mvc.yaml
structura_py/templates/mvcs.yaml
structura_py/utils/__init__.py
structura_py/utils/cmd_utils.py
structura_py/utils/file_utils.py
structura_py/utils/init_utils.py
structura_py/utils/prompt_utils.py
structura_py-1.0.2.dist-info/LICENSE
structura_py-1.0.2.dist-info/METADATA
structura_py-1.0.2.dist-info/WHEEL
structura_py-1.0.2.dist-info/entry_points.txt
structura_py-1.0.2.dist-info/RECORD
