Metadata-Version: 2.3
Name: structura-py
Version: 1.0.2
Summary: Structura is a CLI tool that automates folder structure generation and dependency management for Python projects. It supports multiple architectures (MVC, MVCS, Hexagonal) and frameworks (Flask, FastAPI), using YAML configuration for flexibility.
Author: ShyamSundhar1411
Author-email: clashwithchiefrpjyt@gmail.com
Requires-Python: >=3.11,<4.0
Classifier: Programming Language :: Python :: 3
Classifier: Programming Language :: Python :: 3.11
Classifier: Programming Language :: Python :: 3.12
Classifier: Programming Language :: Python :: 3.13
Requires-Dist: black (>=25.1.0,<26.0.0)
Requires-Dist: flake8 (>=7.2.0,<8.0.0)
Requires-Dist: inquirer (>=3.4.0,<4.0.0)
Requires-Dist: inquirerpy (>=0.3.4,<0.4.0)
Requires-Dist: isort (>=6.0.1,<7.0.0)
Requires-Dist: mypy (>=1.16.1,<2.0.0)
Requires-Dist: pre-commit (>=4.2.0,<5.0.0)
Requires-Dist: pydantic (>=2.11.7,<3.0.0)
Requires-Dist: pyyaml (>=6.0.2,<7.0.0)
Requires-Dist: ruff (>=0.11.13,<0.12.0)
Requires-Dist: typer (>=0.16.0,<0.17.0)
